./.gitignore
./.python-version
./PKG-INFO
./README.md
./__init__.py
./ai.py
./kg_mem.py
./pyproject.toml
./server.py
./storage.py
./uv.lock
./.vscode/launch.json
./ontologies/__init__.py
./ontologies/basic.py
./ontologies/employment.py
./ontologies/github.py
./ontologies/messaging.py
./ontologies/scientific.py
./ontologies/simple_person_project.py
kg_mem-0.1.2.dist-info/METADATA
kg_mem-0.1.2.dist-info/WHEEL
kg_mem-0.1.2.dist-info/entry_points.txt
kg_mem-0.1.2.dist-info/RECORD
