Metadata-Version: 2.4
Name: kg-mem
Version: 0.1.2
Summary: A Model Context Protocol (MCP) server that implements a knowledge graph-based memory system with AI-powered entity and relation extraction
Project-URL: Homepage, https://github.com/belindamo/kg_mem
Project-URL: Repository, https://github.com/belindamo/kg_mem
Requires-Python: >=3.10
Requires-Dist: dspy>=2.6.27
Requires-Dist: fastmcp>=2.10.6
Requires-Dist: mcp>=1.12.1
Requires-Dist: pydantic>=2.11.7
Requires-Dist: pytest-asyncio>=1.1.0
Requires-Dist: pytest>=8.4.1
Provides-Extra: dev
Requires-Dist: pytest; extra == 'dev'
